{"type":"FeatureCollection","features":[{"type":"Feature","id":"fc_pwp_bursa.1","geometry":{"type":"Point","coordinates":[28.38388,40.13769]},"geometry_name":"the_geom","properties":{"fid":1,"id":"buu-lse-02","FC":32.49,"PWP":14.8,"VW_g_cm3":1.45}},{"type":"Feature","id":"fc_pwp_bursa.2","geometry":{"type":"Point","coordinates":[28.38262,40.1391]},"geometry_name":"the_geom","properties":{"fid":2,"id":"buu-lse-03","FC":29.17,"PWP":14.38,"VW_g_cm3":1.47}},{"type":"Feature","id":"fc_pwp_bursa.3","geometry":{"type":"Point","coordinates":[28.38417,40.13674]},"geometry_name":"the_geom","properties":{"fid":3,"id":"buu-lse-05","FC":32.88,"PWP":15.28,"VW_g_cm3":1.42}},{"type":"Feature","id":"fc_pwp_bursa.4","geometry":{"type":"Point","coordinates":[28.38308,40.13753]},"geometry_name":"the_geom","properties":{"fid":4,"id":"buu-lse-07","FC":31.66,"PWP":15.99,"VW_g_cm3":1.44}},{"type":"Feature","id":"fc_pwp_bursa.5","geometry":{"type":"Point","coordinates":[28.38332,40.13663]},"geometry_name":"the_geom","properties":{"fid":5,"id":"buu-lse-09","FC":32.96,"PWP":16.36,"VW_g_cm3":1.43}},{"type":"Feature","id":"fc_pwp_bursa.6","geometry":{"type":"Point","coordinates":[28.38375,40.13898]},"geometry_name":"the_geom","properties":{"fid":6,"id":"buu-lse-10","FC":29.12,"PWP":12.92,"VW_g_cm3":1.5}},{"type":"Feature","id":"fc_pwp_bursa.7","geometry":{"type":"Point","coordinates":[28.38355996,40.13568628]},"geometry_name":"the_geom","properties":{"fid":7,"id":"buu-lse-12","FC":34.03,"PWP":15.74,"VW_g_cm3":1.42}},{"type":"Feature","id":"fc_pwp_bursa.8","geometry":{"type":"Point","coordinates":[28.38251,40.1379]},"geometry_name":"the_geom","properties":{"fid":8,"id":"buu-lse-13","FC":32.21,"PWP":16.09,"VW_g_cm3":1.44}},{"type":"Feature","id":"fc_pwp_bursa.9","geometry":{"type":"Point","coordinates":[28.38446,40.13754]},"geometry_name":"the_geom","properties":{"fid":9,"id":"buu-lse-15","FC":33.86,"PWP":15.01,"VW_g_cm3":1.45}},{"type":"Feature","id":"fc_pwp_bursa.10","geometry":{"type":"Point","coordinates":[28.38276,40.14099]},"geometry_name":"the_geom","properties":{"fid":10,"id":"buu-lse-08","FC":28.07,"PWP":9.87,"VW_g_cm3":1.56}},{"type":"Feature","id":"fc_pwp_bursa.11","geometry":{"type":"Point","coordinates":[28.38278947,40.14003112]},"geometry_name":"the_geom","properties":{"fid":11,"id":"buu-lse-11","FC":28.79,"PWP":11.1,"VW_g_cm3":1.52}},{"type":"Feature","id":"fc_pwp_bursa.12","geometry":{"type":"Point","coordinates":[28.38288,40.14046]},"geometry_name":"the_geom","properties":{"fid":12,"id":"buu-lse-14","FC":27.4,"PWP":6.61,"VW_g_cm3":1.56}},{"type":"Feature","id":"fc_pwp_bursa.13","geometry":{"type":"Point","coordinates":[28.38384,40.14022]},"geometry_name":"the_geom","properties":{"fid":13,"id":"buu-lse-18","FC":28,"PWP":6.87,"VW_g_cm3":1.46}}],"totalFeatures":13,"numberMatched":13,"numberReturned":13,"timeStamp":"2023-03-14T19:27:21.467Z","crs":{"type":"name","properties":{"name":"urn:ogc:def:crs:EPSG::4326"}}}